odoo10_addon_web_widget_char_switchcase-10.0.1.0.1-py2.7-nspkg.pth
odoo/addons/web_widget_char_switchcase/README.rst
odoo/addons/web_widget_char_switchcase/__init__.py
odoo/addons/web_widget_char_switchcase/__manifest__.py
odoo/addons/web_widget_char_switchcase/i18n/web_widget_char_switchcase.pot
odoo/addons/web_widget_char_switchcase/readme/CONFIGURE.rst
odoo/addons/web_widget_char_switchcase/readme/DESCRIPTION.rst
odoo/addons/web_widget_char_switchcase/readme/USAGE.rst
odoo/addons/web_widget_char_switchcase/static/description/index.html
odoo/addons/web_widget_char_switchcase/static/src/js/web_widget_char_switchcase.js
odoo/addons/web_widget_char_switchcase/static/test/web_widget_char_switchcase.js
odoo/addons/web_widget_char_switchcase/tests/__init__.py
odoo/addons/web_widget_char_switchcase/tests/test_js.py
odoo/addons/web_widget_char_switchcase/views/web_widget_char_switchcase.xml
odoo10_addon_web_widget_char_switchcase-10.0.1.0.1.dist-info/METADATA
odoo10_addon_web_widget_char_switchcase-10.0.1.0.1.dist-info/RECORD
odoo10_addon_web_widget_char_switchcase-10.0.1.0.1.dist-info/WHEEL
odoo10_addon_web_widget_char_switchcase-10.0.1.0.1.dist-info/namespace_packages.txt
odoo10_addon_web_widget_char_switchcase-10.0.1.0.1.dist-info/top_level.txt
