Metadata-Version: 2.1
Name: odoo10-addon-web-widget-char-switchcase
Version: 10.0.1.0.1
Summary: Web Char Switchcase Widget
Home-page: https://github.com/OCA/web/tree/10.0/web_widget_char_switchcase
Author: Agile Business Group, Odoo Community Association (OCA)
Author-email: support@odoo-community.org
License: AGPL-3
Platform: UNKNOWN
Classifier: Programming Language :: Python
Classifier: Framework :: Odoo
Classifier: License :: OSI Approved :: GNU Affero General Public License v3
Requires-Python: ~=2.7
Requires-Dist: odoo (<10.1dev,>=10.0)
